odoo/addons/invader_payment_adyen_klarna/README.rst
odoo/addons/invader_payment_adyen_klarna/__init__.py
odoo/addons/invader_payment_adyen_klarna/__manifest__.py
odoo/addons/invader_payment_adyen_klarna/i18n/invader_payment_adyen_klarna.pot
odoo/addons/invader_payment_adyen_klarna/models/__init__.py
odoo/addons/invader_payment_adyen_klarna/models/invader_payable.py
odoo/addons/invader_payment_adyen_klarna/models/payment_transaction.py
odoo/addons/invader_payment_adyen_klarna/readme/CONFIGURE.rst
odoo/addons/invader_payment_adyen_klarna/readme/CONTRIBUTORS.rst
odoo/addons/invader_payment_adyen_klarna/readme/DESCRIPTION.rst
odoo/addons/invader_payment_adyen_klarna/readme/HISTORY.rst
odoo/addons/invader_payment_adyen_klarna/static/description/index.html
odoo14_addon_invader_payment_adyen_klarna-14.0.1.0.2.dist-info/METADATA
odoo14_addon_invader_payment_adyen_klarna-14.0.1.0.2.dist-info/WHEEL
odoo14_addon_invader_payment_adyen_klarna-14.0.1.0.2.dist-info/top_level.txt
odoo14_addon_invader_payment_adyen_klarna-14.0.1.0.2.dist-info/RECORD
